uvic_report_format/__init__.py
uvic_report_format/cli.py
uvic_report_format/compile.py
uvic_report_format/frontmatter.py
uvic_report_format/glossary.py
uvic_report_format/models.py
uvic_report_format/pandoc.py
uvic_report_format/tags
uvic_report_format/templates/frontmatter.md
uvic_report_format/templates/glossary.md
uvic_report_format/templates/titlepage.md
uvic_report_format/test.md
uvic_report_format/utils.py
uvic_report_format-0.1.0.dist-info/entry_points.txt
uvic_report_format-0.1.0.dist-info/WHEEL
uvic_report_format-0.1.0.dist-info/METADATA
uvic_report_format-0.1.0.dist-info/RECORD
